{
  "nom": "La chambre du Phénix",
  "description": "",
  "chapitre": "02_Elementaires",
  "numero": 6,
  "type_restriction": "faction_unique",
  "unites_imposees": [],
  "placement_impose": false,
  "factions_autorisees": [],
  "faction_unique_requise": false,
  "faction_imposee": "",
  "cp_disponible": 8,
  "max_unites": 6,
  "unites_ennemis": [
    [
      "Golem",
      [
        1,
        4
      ]
    ],
    [
      "Golem",
      [
        0,
        5
      ]
    ],
    [
      "Golem",
      [
        1,
        5
      ]
    ],
    [
      "Ifrit",
      [
        5,
        4
      ]
    ],
    [
      "Phénix",
      [
        4,
        4
      ]
    ]
  ],
  "difficulte_ennemis": "normale",
  "recompense_cp": 1,
  "recompense_pa": 0,
  "unites_debloquees": [
    "Esprit"
  ],
  "recompenses_autres": [],
  "completable_plusieurs_fois": false
}