{
  "nom": "Le sanctuaire",
  "description": "Rien",
  "chapitre": "01_Religieux",
  "numero": 4,
  "type_restriction": "faction_unique",
  "unites_imposees": [],
  "placement_impose": false,
  "factions_autorisees": [],
  "faction_unique_requise": false,
  "faction_imposee": "",
  "cp_disponible": 8,
  "max_unites": 8,
  "unites_ennemis": [
    [
      "Missionnaire",
      [
        4,
        4
      ]
    ],
    [
      "Esprit_Saint",
      [
        3,
        5
      ]
    ],
    [
      "Esprit_Saint",
      [
        2,
        5
      ]
    ],
    [
      "Missionnaire",
      [
        3,
        4
      ]
    ],
    [
      "Missionnaire",
      [
        2,
        4
      ]
    ],
    [
      "Clerc",
      [
        1,
        6
      ]
    ],
    [
      "Clerc",
      [
        3,
        6
      ]
    ]
  ],
  "difficulte_ennemis": "normale",
  "recompense_cp": 1,
  "recompense_pa": 80,
  "unites_debloquees": [],
  "recompenses_autres": [],
  "completable_plusieurs_fois": false
}